{
  "id": "publicacao-web/etapa3-producao",
  "title": "Etapa 3 - Produção",
  "description": "Modelagem",
  "source": "@site/docs/21-publicacao-web/etapa3-producao.md",
  "sourceDirName": "21-publicacao-web",
  "slug": "/publicacao-web/etapa3-producao",
  "permalink": "/docs/publicacao-web/etapa3-producao",
  "draft": false,
  "unlisted": false,
  "editUrl": "https://github.com/tcarvi-engenheiro-eduardo-leal/produto-de-artes-visuais/edit/main/tutorial/docs/21-publicacao-web/etapa3-producao.md",
  "tags": [],
  "version": "current",
  "sidebarPosition": 3,
  "frontMatter": {
    "title": "Etapa 3 - Produção",
    "sidebar_position": 3
  },
  "sidebar": "tutorialSidebar",
  "previous": {
    "title": "Etapa 2 - Produção (Insumos para Modelagem)",
    "permalink": "/docs/publicacao-web/etapa2-producao-insumos"
  },
  "next": {
    "title": "Etapa 4 - Pós-Produção",
    "permalink": "/docs/publicacao-web/etapa4-pos-producao"
  }
}